[
    {
        "key": "ǣ-fast",
        "form-raw": "ǣ-fast",
        "type": "adj",
        "gloss": "[religious], [pious]",
        "tags": ["speculative"],
        "origin": "old-english"
    }, {
        "key": "ǣdre-quick",
        "form-raw": "ǣdre",
        "type": "adj",
        "gloss": "[quick] or [instant]",
        "tags": ["speculative"],
        "origin": "old-english"
    }, {
        "key": "ǣġ-wyrt",
        "form-raw": "ǣġ-wyrt",
        "form-canon": "eggwort",
        "type": "noun",
        "gloss": "dandelion",
        "tags": ["count", "concrete", "living", "plant", "speculative"],
        "origin": "old-english"
    }, {
        "key": "cwic-sylfur",
        "form-raw": "cwic-sylfur",
        "form-canon": "quicksilver",
        "type": "noun",
        "gloss": "mercury",
        "tags": ["mass", "concrete", "fluid", "liquid", "metal"],
        "origin": "old-english",
        "notes": "Alternate form 'seolfor'"
    },
    {
        "key": "middan-ġeard",
        "form-raw": "middan-ġeard",
        "type": "noun",
        "gloss": "earth",
        "tags": ["singleton", "concrete", "fluid", "terrain", "speculative"],
        "origin": "old-english"
    },
    {
        "key": "gār-lēac",
        "form-raw": "gār-lēac",
        "form-canon": "garlic",
        "type": "noun",
        "gloss": "garlic",
        "tags": ["mass", "concrete", "living", "plant"],
        "origin": "old-english"
    }
]